gym_vecenv/__init__.py
gym_vecenv/dummy_vec_env.py
gym_vecenv/running_mean_std.py
gym_vecenv/subproc_vec_env.py
gym_vecenv/vec_env.py
gym_vecenv/vec_frame_stack.py
gym_vecenv/vec_normalize.py
gym_vecenv-1.0.dist-info/DESCRIPTION.rst
gym_vecenv-1.0.dist-info/METADATA
gym_vecenv-1.0.dist-info/RECORD
gym_vecenv-1.0.dist-info/WHEEL
gym_vecenv-1.0.dist-info/metadata.json
gym_vecenv-1.0.dist-info/top_level.txt
