Metadata-Version: 2.0
Name: gym-vecenv
Version: 1.0
Summary: Python3 wrapper for running multiple OpenAI Gym compatible environments in parallel
Home-page: https://github.com/agakshat/gym_vecenv
Author: Akshat Agarwal
Author-email: agarwalaks30@gmail.com
License: MIT
Platform: UNKNOWN
Requires-Dist: cloudpickle
Requires-Dist: gym
Requires-Dist: numpy
